{
    "uuid": "8d4ffe6a-a60f-428b-9ff8-ae4406164afd",
    "title": "\u03a6\u03ac\u03c1\u03b5\u03bb \u039f\u03c5\u03af\u03bb\u03b9\u03b1\u03bc\u03c2: \u0394\u03af\u03bd\u03b5\u03b9 1 \u03b5\u03ba\u03b1\u03c4. \u03b4\u03bf\u03bb. \u03c3\u03b5 \u03b5\u03c0\u03b9\u03c7\u03b5\u03b9\u03c1\u03b7\u03bc\u03b1\u03c4\u03af\u03b5\u03c2 \u03ba\u03b1\u03b9\u2026 \u03c0\u03b1\u03af\u03c1\u03bd\u03b5\u03b9 \u03c4\u03bf \u03ba\u03bb\u03b5\u03b9\u03b4\u03af \u03c4\u03bf\u03c5 \u039c\u03b1\u03ca\u03ac\u03bc\u03b9",
    "description": "\u03a3\u03c4\u03bf \u03c0\u03bb\u03b1\u03af\u03c3\u03b9\u03bf \u03c4\u03bf\u03c5 Black Ambition Demo Day, \u03bf Hip Hop \u03b8\u03c1\u03cd\u03bb\u03bf\u03c2 \u03b5\u03c0\u03b9\u03b2\u03c1\u03ac\u03b2\u03b5\u03c5\u03c3\u03b5 25 \u03b1\u03bd\u03b5\u03c1\u03c7\u03cc\u03bc\u03b5\u03bd\u03bf\u03c5\u03c2 \u03b5\u03c0\u03b9\u03c7\u03b5\u03b9\u03c1\u03b7\u03bc\u03b1\u03c4\u03af\u03b5\u03c2 \u03ba\u03b1\u03b9 \u03c4\u03b9\u03bc\u03ae\u03b8\u03b7\u03ba\u03b5 \u03b1\u03c0\u03cc \u03c4\u03b7\u03bd \u03c0\u03cc\u03bb\u03b7 \u03b3\u03b9\u03b1 \u03c4\u03b7\u03bd \u03c0\u03c1\u03bf\u03ce\u03b8\u03b7\u03c3\u03b7 \u03c4\u03b7\u03c2 \u03b5\u03c0\u03b9\u03c7\u03b5\u03b9\u03c1\u03b7\u03bc\u03b1\u03c4\u03b9\u03ba\u03cc\u03c4\u03b7\u03c4\u03b1\u03c2.",
    "keywords": "",
    "snippet": "\u03a3\u03c4\u03bf \u03c0\u03bb\u03b1\u03af\u03c3\u03b9\u03bf \u03c4\u03bf\u03c5 Black Ambition Demo Day, \u03bf Hip Hop \u03b8\u03c1\u03cd\u03bb\u03bf\u03c2 \u03b5\u03c0\u03b9\u03b2\u03c1\u03ac\u03b2\u03b5\u03c5\u03c3\u03b5 25 \u03b1\u03bd\u03b5\u03c1\u03c7\u03cc\u03bc\u03b5\u03bd\u03bf\u03c5\u03c2 \u03b5\u03c0\u03b9\u03c7\u03b5\u03b9\u03c1\u03b7\u03bc\u03b1\u03c4\u03af\u03b5\u03c2 \u03ba...",
    "url": "https://www.fortunegreece.com/article/farel-ouiliams-dinei-1-ekat-dol-se-epixeirimaties-kai-pairnei-to-kleidi-tou-maiami/",
    "image_url": "https://www.fortunegreece.com/wp-content/uploads/2025/11/000_642M788.jpg",
    "language": "el",
    "published_at": "2025-11-19T22:02:54.000000Z",
    "source": "fortunegreece.com",
    "relevance_score": null,
    "entities": [],
    "similar": []
}